janusgraph_python/__init__.py
janusgraph_python/driver/__init__.py
janusgraph_python/driver/serializer.py
janusgraph_python/process/__init__.py
janusgraph_python/process/traversal.py
janusgraph_python/structure/__init__.py
janusgraph_python/structure/io/__init__.py
janusgraph_python/structure/io/graphsonV3d0.py
janusgraph_python/structure/io/util.py
janusgraphpython-1.1.0.data/data/APACHE-2.0.txt
janusgraphpython-1.1.0.data/data/CC-BY-4.0.txt
janusgraphpython-1.1.0.data/data/DCO.txt
janusgraphpython-1.1.0.data/data/LICENSE.txt
janusgraphpython-1.1.0.data/data/requirements.txt
janusgraphpython-1.1.0.dist-info/AUTHORS.txt
janusgraphpython-1.1.0.dist-info/LICENSE.txt
janusgraphpython-1.1.0.dist-info/METADATA
janusgraphpython-1.1.0.dist-info/WHEEL
janusgraphpython-1.1.0.dist-info/top_level.txt
janusgraphpython-1.1.0.dist-info/RECORD
