Metadata-Version: 2.1
Name: janusgraphpython
Version: 1.1.0
Summary: JanusGraph-Python extends Apache TinkerPop™s Gremlin-Python with support for JanusGraph-specific types.
Home-page: https://janusgraph.org/
Author: JanusGraph
License: Apache 2
Classifier: Intended Audience :: Developers
Classifier: License :: OSI Approved :: Apache Software License
Classifier: Natural Language :: English
Classifier: Programming Language :: Python :: 3
License-File: LICENSE.txt
License-File: AUTHORS.txt
Requires-Dist: gremlinpython==3.7.3
